<config>
  <globalProperties>
    <globalProperty>
      <property>datafilter_locationBasedVisitFilter.disabled</property>
      <value>true</value>
    </globalProperty>
    <globalProperty>
      <property>datafilter_locationBasedEncounterFilter.disabled</property>
      <value>true</value>
    </globalProperty>
    <globalProperty>
      <property>datafilter_locationBasedObsFilter.disabled</property>
      <value>true</value>
    </globalProperty>
    <globalProperty>
      <property>datafilter_locationBasedPatientFilter.disabled</property>
      <value>true</value>
    </globalProperty>
    <globalProperty>
      <property>datafilter_locationBasedUserFilter.disabled</property>
      <value>true</value>
    </globalProperty>
    <globalProperty>
      <property>datafilter_locationFilter.disabled</property>
      <value>true</value>
    </globalProperty>
    <globalProperty>
      <property>datafilter_locationBasedDiagnosisFilter.disabled</property>
      <value>true</value>
    </globalProperty>
    <globalProperty>
      <property>datafilter_locationBasedConditionFilter.disabled</property>
      <value>true</value>
    </globalProperty>
    <globalProperty>
      <property>datafilter_programBasedUserFilter.disabled</property>
      <value>true</value>
    </globalProperty>
    <globalProperty>
      <property>datafilter_programBasedProviderFilter.disabled</property>
      <value>true</value>
    </globalProperty>
    <globalProperty>
      <property>datafilter_encTypePrivBasedEncounterFilter.disabled</property>
      <value>true</value>
    </globalProperty>
    <globalProperty>
      <property>datafilter_encTypePrivBasedObsFilter.disabled</property>
      <value>true</value>
    </globalProperty>
    <globalProperty>
      <property>datafilter_encTypePrivBasedConditionFilter.disabled</property>
      <value>true</value>
    </globalProperty>
    <globalProperty>
      <property>datafilter_encTypePrivBasedEncounterTypeFilter.disabled</property>
      <value>true</value>
    </globalProperty>
    <globalProperty>
      <property>datafilter_locationBasedPatientFullTextFilter.disabled</property>
      <value>true</value>
    </globalProperty>
  </globalProperties>
</config>